cfkit/__init__.py
cfkit/_client/__init__.py
cfkit/_client/fetch.py
cfkit/_client/login.py
cfkit/_client/submit.py
cfkit/_cmd/__init__.py
cfkit/_cmd/cli.py
cfkit/_config/__init__.py
cfkit/_config/config.py
cfkit/_config/implementation.py
cfkit/_data/cfkit.conf
cfkit/_data/languages.json
cfkit/_data/test_samples_results.json
cfkit/_data/colorschemes/default.conf
cfkit/_data/colorschemes/named_colors.json
cfkit/_data/resources/history.json
cfkit/_data/resources/session.json
cfkit/_data/resources/problems/1.txt
cfkit/_data/resources/problems/10.txt
cfkit/_data/resources/problems/100.txt
cfkit/_data/resources/problems/1000.txt
cfkit/_data/resources/problems/1001.txt
cfkit/_data/resources/problems/1002.txt
cfkit/_data/resources/problems/1003.txt
cfkit/_data/resources/problems/1004.txt
cfkit/_data/resources/problems/1005.txt
cfkit/_data/resources/problems/1006.txt
cfkit/_data/resources/problems/1007.txt
cfkit/_data/resources/problems/1008.txt
cfkit/_data/resources/problems/1009.txt
cfkit/_data/resources/problems/101.txt
cfkit/_data/resources/problems/1010.txt
cfkit/_data/resources/problems/1011.txt
cfkit/_data/resources/problems/1012.txt
cfkit/_data/resources/problems/1013.txt
cfkit/_data/resources/problems/1014.txt
cfkit/_data/resources/problems/1015.txt
cfkit/_data/resources/problems/1016.txt
cfkit/_data/resources/problems/1017.txt
cfkit/_data/resources/problems/1019.txt
cfkit/_data/resources/problems/102.txt
cfkit/_data/resources/problems/1020.txt
cfkit/_data/resources/problems/1023.txt
cfkit/_data/resources/problems/1025.txt
cfkit/_data/resources/problems/1027.txt
cfkit/_data/resources/problems/1028.txt
cfkit/_data/resources/problems/1029.txt
cfkit/_data/resources/problems/103.txt
cfkit/_data/resources/problems/1030.txt
cfkit/_data/resources/problems/1031.txt
cfkit/_data/resources/problems/1032.txt
cfkit/_data/resources/problems/1033.txt
cfkit/_data/resources/problems/1034.txt
cfkit/_data/resources/problems/1036.txt
cfkit/_data/resources/problems/1037.txt
cfkit-0.0.30.dist-info/licenses/LICENSE.txt
cfkit-0.0.30.dist-info/METADATA
cfkit-0.0.30.dist-info/WHEEL
cfkit-0.0.30.dist-info/entry_points.txt
cfkit-0.0.30.dist-info/top_level.txt
cfkit-0.0.30.dist-info/RECORD
