Metadata-Version: 2.4
Name: cfkit
Version: 0.0.30
Summary: A tool for managing coding competitions.
Home-page: https://github.com/ghoudiy/cfkit
Author: Yassine Ghoudi
Author-email: ghoudi.dev@gmail.com
Project-URL: Issues, https://github.com/ghoudiy/cfkit/issues
Keywords: CLI,Python,competition,management
Classifier: Programming Language :: Python :: 3
Classifier: License :: OSI Approved :: MIT License
Classifier: Operating System :: OS Independent
Requires-Python: >=3.8
License-File: LICENSE.txt
Requires-Dist: MechanicalSoup>=1.3.0
Requires-Dist: beautifulsoup4>=4.10.0
Requires-Dist: prompt_toolkit>=3.0.36
Requires-Dist: cloudscraper>=1.2.71
Dynamic: author
Dynamic: author-email
Dynamic: classifier
Dynamic: description
Dynamic: description-content-type
Dynamic: home-page
Dynamic: keywords
Dynamic: license-file
Dynamic: project-url
Dynamic: requires-dist
Dynamic: requires-python
Dynamic: summary
